django_github_webhook/__init__.py
django_github_webhook/views.py
django_static_push/__init__.py
django_static_push/middleware.py
django_static_push/templatetags/staticpush.py
django_static_push-0.1.0.dist-info/DESCRIPTION.rst
django_static_push-0.1.0.dist-info/METADATA
django_static_push-0.1.0.dist-info/RECORD
django_static_push-0.1.0.dist-info/WHEEL
django_static_push-0.1.0.dist-info/metadata.json
django_static_push-0.1.0.dist-info/top_level.txt
