Metadata-Version: 2.0
Name: django-static-push
Version: 0.1.0
Summary: Django staticfiles extension for HTTP/2 push
Home-page: https://github.com/fladi/django-static-push
Author: Michael Fladischer
Author-email: michael@openservices.at
License: BSD
Keywords: django,middleware,templatetag,static,assets,http/2,push
Platform: UNKNOWN
Classifier: Development Status :: 5 - Production/Stable
Classifier: Intended Audience :: Developers
Classifier: License :: OSI Approved :: BSD License
Classifier: Programming Language :: Python
Classifier: Programming Language :: Python :: 3
Classifier: Programming Language :: Python :: 3.4
Classifier: Programming Language :: Python :: 3.5
Classifier: Programming Language :: Python :: Implementation :: CPython
Classifier: Programming Language :: Python :: Implementation :: PyPy
Classifier: Topic :: Utilities
Requires-Dist: Django (>=1.10)
